[{"line":2,"elements":[{"line":4,"name":"","description":"","type":"background","keyword":"Background","steps":[{"result":{"duration":3774659400,"status":"passed"},"line":5,"name":"I can access WebDriver university website","match":{"location":"stepDefinitions.Login.iCanAccessWebDriverUniversityWebsite()"},"after":[{"result":{"status":"passed"},"match":{"location":"stepDefinitions.base.Hooks.captureExeptionImage(io.cucumber.java.Scenario)"}}],"keyword":"Given "}]},{"start_timestamp":"2025-01-21T11:23:46.933Z","before":[{"result":{"duration":3967656400,"status":"passed"},"match":{"location":"stepDefinitions.base.Hooks.setup()"}}],"line":16,"name":"Validate - Unsuccessful and Unsuccessful Login","description":"","id":"webdriver-university---login;validate---unsuccessful-and-unsuccessful-login;;2","after":[{"result":{"duration":531038600,"status":"passed"},"match":{"location":"stepDefinitions.base.Hooks.tearDown()"}}],"type":"scenario","keyword":"Scenario Outline","steps":[{"result":{"duration":734868200,"status":"passed"},"line":9,"name":"I enter a username webdriver","match":{"arguments":[{"val":"webdriver","offset":19}],"location":"stepDefinitions.Login.iEnterAUsername(java.lang.String)"},"after":[{"result":{"status":"passed"},"match":{"location":"stepDefinitions.base.Hooks.captureExeptionImage(io.cucumber.java.Scenario)"}}],"keyword":"When "},{"result":{"duration":502959900,"status":"passed"},"line":10,"name":"I enter a password webdriver123","match":{"arguments":[{"val":"webdriver123","offset":19}],"location":"stepDefinitions.Login.iEnterAPassword(java.lang.String)"},"after":[{"result":{"status":"passed"},"match":{"location":"stepDefinitions.base.Hooks.captureExeptionImage(io.cucumber.java.Scenario)"}}],"keyword":"And "},{"result":{"duration":366461400,"status":"passed"},"line":11,"name":"I click on login","match":{"location":"stepDefinitions.Login.iClickOnLogin()"},"after":[{"result":{"status":"passed"},"match":{"location":"stepDefinitions.base.Hooks.captureExeptionImage(io.cucumber.java.Scenario)"}}],"keyword":"And "},{"result":{"duration":58297700,"status":"passed"},"line":12,"name":"I should be presented with the following login message validation succeeded","match":{"arguments":[{"val":"validation succeeded","offset":55}],"location":"stepDefinitions.Login.iShouldBePresentedWithTheFollowingLoginMessage(java.lang.String)"},"after":[{"result":{"duration":1337600,"status":"passed"},"match":{"location":"stepDefinitions.base.Hooks.captureExeptionImage(io.cucumber.java.Scenario)"}}],"keyword":"Then "}],"tags":[{"name":"@login"},{"name":"@regression"}]},{"line":4,"name":"","description":"","type":"background","keyword":"Background","steps":[{"result":{"duration":739075000,"status":"passed"},"line":5,"name":"I can access WebDriver university website","match":{"location":"stepDefinitions.Login.iCanAccessWebDriverUniversityWebsite()"},"after":[{"result":{"duration":3456400,"status":"passed"},"match":{"location":"stepDefinitions.base.Hooks.captureExeptionImage(io.cucumber.java.Scenario)"}}],"keyword":"Given "}]},{"start_timestamp":"2025-01-21T11:23:46.933Z","before":[{"result":{"duration":7274215100,"status":"passed"},"match":{"location":"stepDefinitions.base.Hooks.setup()"}}],"line":17,"name":"Validate - Unsuccessful and Unsuccessful Login","description":"","id":"webdriver-university---login;validate---unsuccessful-and-unsuccessful-login;;3","after":[{"result":{"duration":399343200,"status":"passed"},"match":{"location":"stepDefinitions.base.Hooks.tearDown()"}}],"type":"scenario","keyword":"Scenario Outline","steps":[{"result":{"duration":2328079500,"status":"passed"},"line":9,"name":"I enter a username webdriver","match":{"arguments":[{"val":"webdriver","offset":19}],"location":"stepDefinitions.Login.iEnterAUsername(java.lang.String)"},"after":[{"result":{"duration":1554700,"status":"passed"},"match":{"location":"stepDefinitions.base.Hooks.captureExeptionImage(io.cucumber.java.Scenario)"}}],"keyword":"When "},{"result":{"duration":418398800,"status":"passed"},"line":10,"name":"I enter a password webdriver1","match":{"arguments":[{"val":"webdriver1","offset":19}],"location":"stepDefinitions.Login.iEnterAPassword(java.lang.String)"},"after":[{"result":{"status":"passed"},"match":{"location":"stepDefinitions.base.Hooks.captureExeptionImage(io.cucumber.java.Scenario)"}}],"keyword":"And "},{"result":{"duration":268943600,"status":"passed"},"line":11,"name":"I click on login","match":{"location":"stepDefinitions.Login.iClickOnLogin()"},"after":[{"result":{"duration":2115200,"status":"passed"},"match":{"location":"stepDefinitions.base.Hooks.captureExeptionImage(io.cucumber.java.Scenario)"}}],"keyword":"And "},{"result":{"duration":7753300,"status":"passed"},"line":12,"name":"I should be presented with the following login message validation failed","match":{"arguments":[{"val":"validation failed","offset":55}],"location":"stepDefinitions.Login.iShouldBePresentedWithTheFollowingLoginMessage(java.lang.String)"},"after":[{"result":{"status":"passed"},"match":{"location":"stepDefinitions.base.Hooks.captureExeptionImage(io.cucumber.java.Scenario)"}}],"keyword":"Then "}],"tags":[{"name":"@login"},{"name":"@regression"}]},{"line":4,"name":"","description":"","type":"background","keyword":"Background","steps":[{"result":{"duration":1247184800,"status":"passed"},"line":5,"name":"I can access WebDriver university website","match":{"location":"stepDefinitions.Login.iCanAccessWebDriverUniversityWebsite()"},"after":[{"result":{"duration":7336200,"status":"passed"},"match":{"location":"stepDefinitions.base.Hooks.captureExeptionImage(io.cucumber.java.Scenario)"}}],"keyword":"Given "}]},{"start_timestamp":"2025-01-21T11:23:46.937Z","before":[{"result":{"duration":5356186100,"status":"passed"},"match":{"location":"stepDefinitions.base.Hooks.setup()"}}],"line":18,"name":"Validate - Unsuccessful and Unsuccessful Login","description":"","id":"webdriver-university---login;validate---unsuccessful-and-unsuccessful-login;;4","after":[{"result":{"duration":534440100,"status":"passed"},"match":{"location":"stepDefinitions.base.Hooks.tearDown()"}}],"type":"scenario","keyword":"Scenario Outline","steps":[{"result":{"duration":2314630000,"status":"passed"},"line":9,"name":"I enter a username joe_blogs","match":{"arguments":[{"val":"joe_blogs","offset":19}],"location":"stepDefinitions.Login.iEnterAUsername(java.lang.String)"},"after":[{"result":{"duration":2012800,"status":"passed"},"match":{"location":"stepDefinitions.base.Hooks.captureExeptionImage(io.cucumber.java.Scenario)"}}],"keyword":"When "},{"result":{"duration":337652000,"status":"passed"},"line":10,"name":"I enter a password password1","match":{"arguments":[{"val":"password1","offset":19}],"location":"stepDefinitions.Login.iEnterAPassword(java.lang.String)"},"after":[{"result":{"status":"passed"},"match":{"location":"stepDefinitions.base.Hooks.captureExeptionImage(io.cucumber.java.Scenario)"}}],"keyword":"And "},{"result":{"duration":670292000,"status":"passed"},"line":11,"name":"I click on login","match":{"location":"stepDefinitions.Login.iClickOnLogin()"},"after":[{"result":{"duration":1605400,"status":"passed"},"match":{"location":"stepDefinitions.base.Hooks.captureExeptionImage(io.cucumber.java.Scenario)"}}],"keyword":"And "},{"result":{"duration":44096000,"status":"passed"},"line":12,"name":"I should be presented with the following login message validation failed","match":{"arguments":[{"val":"validation failed","offset":55}],"location":"stepDefinitions.Login.iShouldBePresentedWithTheFollowingLoginMessage(java.lang.String)"},"after":[{"result":{"status":"passed"},"match":{"location":"stepDefinitions.base.Hooks.captureExeptionImage(io.cucumber.java.Scenario)"}}],"keyword":"Then "}],"tags":[{"name":"@login"},{"name":"@regression"}]}],"name":"WebDriver University - Login","description":"","id":"webdriver-university---login","keyword":"Feature","uri":"file:src/test/resources/features/Login.feature","tags":[{"name":"@login","type":"Tag","location":{"line":1,"column":1}},{"name":"@regression","type":"Tag","location":{"line":1,"column":8}}]}]